{"_ts":[1612378413,1612724966,1613071477,1613417567,1613762586],"_r":{"breakdown":{"html":{"bytes":[25757,25633,25726,25710,25650],"requests":[2,2,2,2,2]},"js":{"bytes":[202377,202578,202472,202377,202377],"requests":[9,9,9,9,9]},"css":{"bytes":[123918,123920,124137,124219,124131],"requests":[4,4,4,4,4]},"image":{"bytes":[48894,48894,48946,48899,48997],"requests":[7,7,7,7,7]},"flash":{"bytes":[0,0,0,0,0],"requests":[0,0,0,0,0]},"font":{"bytes":[61624,61624,61624,61624,61624],"requests":[2,2,2,2,2]},"video":{"bytes":[0,0,0,0,0],"requests":[0,0,0,0,0]},"other":{"bytes":[0,0,0,0,0],"requests":[0,0,0,0,0]}},"date":[1612378413,1612724966,1613071477,1613417567,1613762586],"domElements":[2439,2433,2434,2434,2434],"domInteractive":[5277,5245,5210,5337,5181],"firstPaint":[4647.799999998824,4759.729999997944,4596.979999998439,4830.835000000661,4489.574999999604],"fullyLoaded":[7710,7643,7546,7555,7408],"id":["210203_Di4B_a6f99a56416a8f782971ca3ed78f2f61","210207_DiEE_9be83a47588961cb4407afde20ee09f1","210211_DiBH_8132735500d82c70acf9556a8838f675","210215_DiH5_e57ccd568a7cb50223b1f7767b50b07f","210219_DiCZ_65d72bb867248221db95bfc05455d8c7"],"loadTime":[7326,7271,7139,7155,7037],"render":[4700,4800,4600,4900,4500],"SpeedIndex":[8335,8341,8200,8258,8102],"TTFB":[3073,3064,3037,3111,3035],"videoFrames":[[{"_i":"ms_000000.jpg","_t":0,"_vc":0},{"_i":"ms_004800.jpg","_t":4800,"_vc":13},{"_i":"ms_005300.jpg","_t":5300,"_vc":14},{"_i":"ms_005900.jpg","_t":5900,"_vc":12},{"_i":"ms_006000.jpg","_t":6000,"_vc":12},{"_i":"ms_007100.jpg","_t":7100,"_vc":12},{"_i":"ms_008400.jpg","_t":8400,"_vc":19},{"_i":"ms_008500.jpg","_t":8500,"_vc":18},{"_i":"ms_008600.jpg","_t":8600,"_vc":20},{"_i":"ms_008700.jpg","_t":8700,"_vc":21},{"_i":"ms_008800.jpg","_t":8800,"_vc":28},{"_i":"ms_008900.jpg","_t":8900,"_vc":96},{"_i":"ms_009000.jpg","_t":9000,"_vc":99},{"_i":"ms_009100.jpg","_t":9100,"_vc":100}],[{"_i":"ms_000000.jpg","_t":0,"_vc":0},{"_i":"ms_004800.jpg","_t":4800,"_vc":13},{"_i":"ms_005400.jpg","_t":5400,"_vc":14},{"_i":"ms_005900.jpg","_t":5900,"_vc":12},{"_i":"ms_006100.jpg","_t":6100,"_vc":12},{"_i":"ms_007100.jpg","_t":7100,"_vc":13},{"_i":"ms_007700.jpg","_t":7700,"_vc":12},{"_i":"ms_007800.jpg","_t":7800,"_vc":12},{"_i":"ms_008400.jpg","_t":8400,"_vc":16},{"_i":"ms_008500.jpg","_t":8500,"_vc":17},{"_i":"ms_008600.jpg","_t":8600,"_vc":18},{"_i":"ms_008700.jpg","_t":8700,"_vc":26},{"_i":"ms_008800.jpg","_t":8800,"_vc":31},{"_i":"ms_008900.jpg","_t":8900,"_vc":98},{"_i":"ms_009000.jpg","_t":9000,"_vc":99},{"_i":"ms_009100.jpg","_t":9100,"_vc":100}],[{"_i":"ms_000000.jpg","_t":0,"_vc":0},{"_i":"ms_004600.jpg","_t":4600,"_vc":13},{"_i":"ms_005400.jpg","_t":5400,"_vc":14},{"_i":"ms_006500.jpg","_t":6500,"_vc":12},{"_i":"ms_007100.jpg","_t":7100,"_vc":13},{"_i":"ms_007500.jpg","_t":7500,"_vc":12},{"_i":"ms_007600.jpg","_t":7600,"_vc":12},{"_i":"ms_008200.jpg","_t":8200,"_vc":15},{"_i":"ms_008300.jpg","_t":8300,"_vc":17},{"_i":"ms_008400.jpg","_t":8400,"_vc":20},{"_i":"ms_008500.jpg","_t":8500,"_vc":26},{"_i":"ms_008600.jpg","_t":8600,"_vc":31},{"_i":"ms_008700.jpg","_t":8700,"_vc":98},{"_i":"ms_008800.jpg","_t":8800,"_vc":99},{"_i":"ms_008900.jpg","_t":8900,"_vc":100}],[{"_i":"ms_000000.jpg","_t":0,"_vc":0},{"_i":"ms_004700.jpg","_t":4700,"_vc":13},{"_i":"ms_005400.jpg","_t":5400,"_vc":14},{"_i":"ms_006600.jpg","_t":6600,"_vc":12},{"_i":"ms_007100.jpg","_t":7100,"_vc":12},{"_i":"ms_008300.jpg","_t":8300,"_vc":12},{"_i":"ms_008400.jpg","_t":8400,"_vc":17},{"_i":"ms_008500.jpg","_t":8500,"_vc":20},{"_i":"ms_008600.jpg","_t":8600,"_vc":23},{"_i":"ms_008700.jpg","_t":8700,"_vc":28},{"_i":"ms_008800.jpg","_t":8800,"_vc":32},{"_i":"ms_008900.jpg","_t":8900,"_vc":98},{"_i":"ms_009000.jpg","_t":9000,"_vc":100}],[{"_i":"ms_000000.jpg","_t":0,"_vc":0},{"_i":"ms_004600.jpg","_t":4600,"_vc":13},{"_i":"ms_005300.jpg","_t":5300,"_vc":14},{"_i":"ms_006500.jpg","_t":6500,"_vc":12},{"_i":"ms_007000.jpg","_t":7000,"_vc":12},{"_i":"ms_007400.jpg","_t":7400,"_vc":12},{"_i":"ms_007500.jpg","_t":7500,"_vc":12},{"_i":"ms_007600.jpg","_t":7600,"_vc":12},{"_i":"ms_008100.jpg","_t":8100,"_vc":12},{"_i":"ms_008200.jpg","_t":8200,"_vc":16},{"_i":"ms_008300.jpg","_t":8300,"_vc":18},{"_i":"ms_008400.jpg","_t":8400,"_vc":21},{"_i":"ms_008500.jpg","_t":8500,"_vc":26},{"_i":"ms_008600.jpg","_t":8600,"_vc":30},{"_i":"ms_008700.jpg","_t":8700,"_vc":98},{"_i":"ms_008800.jpg","_t":8800,"_vc":99},{"_i":"ms_008900.jpg","_t":8900,"_vc":100}]],"visualComplete":[9100,9100,8900,9000,8800],"lighthouse":[61,57,59,54,57],"pagespeed":[null,null,null,null,null]}}