{"_ts":[1593808721,1594155221,1594500826,1594920286],"_r":{"breakdown":{"html":{"bytes":[27285,27284,27294,27290],"requests":[2,2,2,2]},"js":{"bytes":[201727,201727,201642,201685],"requests":[11,11,11,11]},"css":{"bytes":[122510,122510,122494,122645],"requests":[5,5,5,5]},"image":{"bytes":[956671,956671,956671,956671],"requests":[46,46,46,46]},"flash":{"bytes":[0,0,0,0],"requests":[0,0,0,0]},"font":{"bytes":[61624,61624,61624,61624],"requests":[2,2,2,2]},"video":{"bytes":[0,0,0,0],"requests":[0,0,0,0]},"other":{"bytes":[0,0,0,0],"requests":[0,0,0,0]}},"date":[1593808721,1594155221,1594500826,1594920286],"domElements":[2413,2413,2413,2413],"domInteractive":[4616,4695,4788,4937],"firstPaint":[4341.930000000048,4452.539999999999,4475.794999991194,4634.17500000287],"fullyLoaded":[12090,12025,12310,12339],"id":["200703_4A_05594b18e7713849c835ed6dd67c5cf9","200707_SW_4a69b5638c3c8cd145cda4e9fb3d810d","200711_WJ_fac0a5f351ff34483bca85d68e9e9f93","200716_G4_55dfa92645137aa78b9ddfbc6b586625"],"loadTime":[11678,11608,11785,11882],"render":[4300,4400,4400,4600],"SpeedIndex":[7299,7330,7509,7633],"TTFB":[2080,2098,2111,2137],"videoFrames":[[{"_i":"ms_000000.jpg","_t":0,"_vc":0},{"_i":"ms_004400.jpg","_t":4400,"_vc":24},{"_i":"ms_004500.jpg","_t":4500,"_vc":21},{"_i":"ms_004700.jpg","_t":4700,"_vc":68},{"_i":"ms_004800.jpg","_t":4800,"_vc":68},{"_i":"ms_005400.jpg","_t":5400,"_vc":68},{"_i":"ms_005500.jpg","_t":5500,"_vc":67},{"_i":"ms_005600.jpg","_t":5600,"_vc":67},{"_i":"ms_005700.jpg","_t":5700,"_vc":66},{"_i":"ms_005800.jpg","_t":5800,"_vc":66},{"_i":"ms_007600.jpg","_t":7600,"_vc":67},{"_i":"ms_008200.jpg","_t":8200,"_vc":67},{"_i":"ms_008300.jpg","_t":8300,"_vc":66},{"_i":"ms_008500.jpg","_t":8500,"_vc":67},{"_i":"ms_009100.jpg","_t":9100,"_vc":67},{"_i":"ms_009200.jpg","_t":9200,"_vc":66},{"_i":"ms_009300.jpg","_t":9300,"_vc":67},{"_i":"ms_010200.jpg","_t":10200,"_vc":67},{"_i":"ms_010300.jpg","_t":10300,"_vc":66},{"_i":"ms_010400.jpg","_t":10400,"_vc":67},{"_i":"ms_010900.jpg","_t":10900,"_vc":67},{"_i":"ms_011000.jpg","_t":11000,"_vc":67},{"_i":"ms_011100.jpg","_t":11100,"_vc":67},{"_i":"ms_011400.jpg","_t":11400,"_vc":67},{"_i":"ms_011900.jpg","_t":11900,"_vc":67},{"_i":"ms_012000.jpg","_t":12000,"_vc":67},{"_i":"ms_012100.jpg","_t":12100,"_vc":67},{"_i":"ms_012600.jpg","_t":12600,"_vc":67},{"_i":"ms_012700.jpg","_t":12700,"_vc":68},{"_i":"ms_012800.jpg","_t":12800,"_vc":69},{"_i":"ms_012900.jpg","_t":12900,"_vc":69},{"_i":"ms_013000.jpg","_t":13000,"_vc":71},{"_i":"ms_013100.jpg","_t":13100,"_vc":73},{"_i":"ms_013200.jpg","_t":13200,"_vc":76},{"_i":"ms_013300.jpg","_t":13300,"_vc":98},{"_i":"ms_013400.jpg","_t":13400,"_vc":100}],[{"_i":"ms_000000.jpg","_t":0,"_vc":0},{"_i":"ms_004200.jpg","_t":4200,"_vc":24},{"_i":"ms_004300.jpg","_t":4300,"_vc":24},{"_i":"ms_004400.jpg","_t":4400,"_vc":21},{"_i":"ms_004600.jpg","_t":4600,"_vc":68},{"_i":"ms_004800.jpg","_t":4800,"_vc":67},{"_i":"ms_005500.jpg","_t":5500,"_vc":66},{"_i":"ms_005600.jpg","_t":5600,"_vc":66},{"_i":"ms_005800.jpg","_t":5800,"_vc":67},{"_i":"ms_006300.jpg","_t":6300,"_vc":67},{"_i":"ms_006400.jpg","_t":6400,"_vc":67},{"_i":"ms_006500.jpg","_t":6500,"_vc":66},{"_i":"ms_008300.jpg","_t":8300,"_vc":67},{"_i":"ms_009100.jpg","_t":9100,"_vc":67},{"_i":"ms_009200.jpg","_t":9200,"_vc":67},{"_i":"ms_009300.jpg","_t":9300,"_vc":66},{"_i":"ms_009400.jpg","_t":9400,"_vc":66},{"_i":"ms_010400.jpg","_t":10400,"_vc":67},{"_i":"ms_011000.jpg","_t":11000,"_vc":67},{"_i":"ms_011100.jpg","_t":11100,"_vc":66},{"_i":"ms_011300.jpg","_t":11300,"_vc":67},{"_i":"ms_011400.jpg","_t":11400,"_vc":67},{"_i":"ms_011600.jpg","_t":11600,"_vc":67},{"_i":"ms_011800.jpg","_t":11800,"_vc":67},{"_i":"ms_011900.jpg","_t":11900,"_vc":67},{"_i":"ms_012700.jpg","_t":12700,"_vc":67},{"_i":"ms_012800.jpg","_t":12800,"_vc":68},{"_i":"ms_012900.jpg","_t":12900,"_vc":68},{"_i":"ms_013000.jpg","_t":13000,"_vc":70},{"_i":"ms_013100.jpg","_t":13100,"_vc":71},{"_i":"ms_013200.jpg","_t":13200,"_vc":73},{"_i":"ms_013300.jpg","_t":13300,"_vc":97},{"_i":"ms_013400.jpg","_t":13400,"_vc":98},{"_i":"ms_013500.jpg","_t":13500,"_vc":100}],[{"_i":"ms_000000.jpg","_t":0,"_vc":0},{"_i":"ms_004400.jpg","_t":4400,"_vc":24},{"_i":"ms_004500.jpg","_t":4500,"_vc":21},{"_i":"ms_004600.jpg","_t":4600,"_vc":67},{"_i":"ms_005800.jpg","_t":5800,"_vc":66},{"_i":"ms_005900.jpg","_t":5900,"_vc":66},{"_i":"ms_006100.jpg","_t":6100,"_vc":67},{"_i":"ms_006600.jpg","_t":6600,"_vc":67},{"_i":"ms_006700.jpg","_t":6700,"_vc":66},{"_i":"ms_006800.jpg","_t":6800,"_vc":66},{"_i":"ms_010200.jpg","_t":10200,"_vc":67},{"_i":"ms_011000.jpg","_t":11000,"_vc":67},{"_i":"ms_011100.jpg","_t":11100,"_vc":66},{"_i":"ms_011200.jpg","_t":11200,"_vc":66},{"_i":"ms_011300.jpg","_t":11300,"_vc":67},{"_i":"ms_011600.jpg","_t":11600,"_vc":67},{"_i":"ms_011800.jpg","_t":11800,"_vc":67},{"_i":"ms_011900.jpg","_t":11900,"_vc":67},{"_i":"ms_012000.jpg","_t":12000,"_vc":67},{"_i":"ms_012900.jpg","_t":12900,"_vc":67},{"_i":"ms_013000.jpg","_t":13000,"_vc":68},{"_i":"ms_013100.jpg","_t":13100,"_vc":69},{"_i":"ms_013200.jpg","_t":13200,"_vc":71},{"_i":"ms_013300.jpg","_t":13300,"_vc":74},{"_i":"ms_013400.jpg","_t":13400,"_vc":77},{"_i":"ms_013500.jpg","_t":13500,"_vc":99},{"_i":"ms_013600.jpg","_t":13600,"_vc":100}],[{"_i":"ms_000000.jpg","_t":0,"_vc":0},{"_i":"ms_004400.jpg","_t":4400,"_vc":23},{"_i":"ms_004600.jpg","_t":4600,"_vc":21},{"_i":"ms_004700.jpg","_t":4700,"_vc":65},{"_i":"ms_004800.jpg","_t":4800,"_vc":65},{"_i":"ms_005400.jpg","_t":5400,"_vc":65},{"_i":"ms_005500.jpg","_t":5500,"_vc":65},{"_i":"ms_005600.jpg","_t":5600,"_vc":65},{"_i":"ms_005700.jpg","_t":5700,"_vc":65},{"_i":"ms_005800.jpg","_t":5800,"_vc":64},{"_i":"ms_006000.jpg","_t":6000,"_vc":64},{"_i":"ms_006200.jpg","_t":6200,"_vc":64},{"_i":"ms_006300.jpg","_t":6300,"_vc":64},{"_i":"ms_006400.jpg","_t":6400,"_vc":64},{"_i":"ms_008000.jpg","_t":8000,"_vc":64},{"_i":"ms_008500.jpg","_t":8500,"_vc":64},{"_i":"ms_008600.jpg","_t":8600,"_vc":64},{"_i":"ms_008700.jpg","_t":8700,"_vc":64},{"_i":"ms_009500.jpg","_t":9500,"_vc":64},{"_i":"ms_010101.jpg","_t":10101,"_vc":64},{"_i":"ms_010200.jpg","_t":10200,"_vc":64},{"_i":"ms_011100.jpg","_t":11100,"_vc":64},{"_i":"ms_011500.jpg","_t":11500,"_vc":65},{"_i":"ms_011700.jpg","_t":11700,"_vc":64},{"_i":"ms_011800.jpg","_t":11800,"_vc":64},{"_i":"ms_012600.jpg","_t":12600,"_vc":64},{"_i":"ms_012700.jpg","_t":12700,"_vc":66},{"_i":"ms_012800.jpg","_t":12800,"_vc":66},{"_i":"ms_012900.jpg","_t":12900,"_vc":68},{"_i":"ms_013000.jpg","_t":13000,"_vc":70},{"_i":"ms_013100.jpg","_t":13100,"_vc":73},{"_i":"ms_013200.jpg","_t":13200,"_vc":97},{"_i":"ms_013300.jpg","_t":13300,"_vc":98},{"_i":"ms_013400.jpg","_t":13400,"_vc":100}]],"visualComplete":[13300,13300,13600,13000],"lighthouse":[77,77,57,62],"pagespeed":[null,null,null,null]}}